wrapworks/__init__.py
wrapworks/error_handling.py
wrapworks/files.py
wrapworks/importing.py
wrapworks/wraps.py
wrapworks/tests/__init__.py
wrapworks/tests/test_error_handling.py
wrapworks/tests/test_wraps.py
wrapworks-1.1.2.dist-info/METADATA
wrapworks-1.1.2.dist-info/WHEEL
wrapworks-1.1.2.dist-info/top_level.txt
wrapworks-1.1.2.dist-info/RECORD
