Metadata-Version: 2.4
Name: wrapworks
Version: 1.1.2
Summary: Decorators for Developers
Author-email: Asaniczka <asaniczka@gmail.com>
Maintainer-email: Asaniczka <asaniczka@gmail.com>
License: Apache-2.0
Project-URL: Homepage, https://github.com/asaniczka/wrapworks
Classifier: Development Status :: 4 - Beta
Classifier: Intended Audience :: Developers
Classifier: License :: OSI Approved :: Apache Software License
Classifier: Natural Language :: English
Classifier: Programming Language :: Python :: 3.10
Requires-Python: >=3.10
Requires-Dist: python-dotenv>=0.5.0
Requires-Dist: rich>=11.0.0
